django_migration_vis/__init__.py
django_migration_vis/management/__init__.py
django_migration_vis/management/commands/__init__.py
django_migration_vis/management/commands/visualizemigrations.py
django_migration_vis-2.0.1.dist-info/METADATA
django_migration_vis-2.0.1.dist-info/WHEEL
django_migration_vis-2.0.1.dist-info/top_level.txt
django_migration_vis-2.0.1.dist-info/RECORD
